mycolours/__init__.py
mycolours/run.py
mycolours-0.0.1.dist-info/LICENSE
mycolours-0.0.1.dist-info/METADATA
mycolours-0.0.1.dist-info/WHEEL
mycolours-0.0.1.dist-info/top_level.txt
mycolours-0.0.1.dist-info/RECORD
